[1,["ebLUSQYVRMgZbbKrfpPB7f@f9941","bcVcmjxF5MPaPu8K46SzI1@6c48a","bcVcmjxF5MPaPu8K46SzI1@f9941","ebLUSQYVRMgZbbKrfpPB7f@6c48a"],["node","_textureSource","root","_target","target","data","_spriteFrame","_normalSprite","_hoverSprite","_pressedSprite"],["cc.SpriteFrame",["cc.Prefab",["_name"],2],["cc.Node",["_name","_layer","_components","_prefab"],1,9,4],["cc.UITransform",["node","__prefab","_contentSize"],3,1,4,5],["cc.CompPrefabInfo",["fileId"],2],["cc.Sprite",["_sizeMode","_isTrimmedMode","node","__prefab","_spriteFrame"],1,1,4,6],["cc.Button",["_transition","node","__prefab","clickEvents","_normalColor","_target","_normalSprite","_hoverSprite","_pressedSprite"],2,1,4,9,5,1,6,6,6],["cc.ClickEvent",["_componentId","handler","target"],1,1],["53da3pjk/BOV7S/FsIcamQT",["node","__prefab"],3,1,4],["cc.PrefabInfo",["fileId","root","asset"],2,1,1]],[[4,0,2],[1,0,2],[2,0,1,2,3,3],[3,0,1,2,1],[5,0,1,2,3,4,3],[6,0,1,2,3,4,5,6,7,8,2],[7,0,1,2,3],[8,0,1,1],[9,0,1,2,2]],[[[{"name":"Gopher2","rect":{"x":0,"y":46,"width":102,"height":56},"offset":{"x":0,"y":-23},"originalSize":{"width":102,"height":102},"rotated":false,"capInsets":[0,0,0,0],"packable":true}],[0],0,[0],[1],[1]],[[[1,"Gopher"],[2,"Gopher",33554432,[[3,-2,[0,"9eocz6CKBEM7K/CoNWoGZt"],[5,102,102]],[4,2,false,-3,[0,"660bbm22JNnqomEQxgTIlv"],0],[5,2,-6,[0,"d7XpFZuEtEPIyZOaondJ6W"],[[6,"53da3pjk/BOV7S/FsIcamQT","onClickEvent",-5]],[4,4292269782],-4,1,2,3],[7,-7,[0,"0em4o5JpFJp6NBnpgKNvqG"]]],[8,"afpCrm/ZpBNrmbmRTPa+qZ",-1,0]]],0,[0,2,1,0,0,1,0,0,1,0,3,1,0,4,1,0,0,1,0,0,1,0,5,1,7],[0,0,0,0],[6,7,8,9],[0,0,0,2]],[[{"name":"Gopher1","rect":{"x":0,"y":17,"width":102,"height":85},"offset":{"x":0,"y":-8.5},"originalSize":{"width":102,"height":102},"rotated":false,"capInsets":[0,0,0,0],"packable":true}],[0],0,[0],[1],[3]]]]
